radars/__init__.py
radars/mather.py
radars/randomer.py
tests/__init__.py
radars-0.0.2.dist-info/METADATA
radars-0.0.2.dist-info/WHEEL
radars-0.0.2.dist-info/top_level.txt
radars-0.0.2.dist-info/RECORD
