Metadata-Version: 2.1
Name: radars
Version: 0.0.2
Summary: Trying to publish something
Home-page: https://imtiyaz-ali.github.io/radars/
Author: emteyaz
Author-email: emteyazalee@gmail.com
License: UNKNOWN
Project-URL: Bug Tracker, https://github.com/Imtiyaz-ali/radars/issues
Platform: UNKNOWN
Classifier: Programming Language :: Python :: 3
Classifier: License :: OSI Approved :: MIT License
Classifier: Operating System :: OS Independent
